{"id":"466","name":"Conquering the Academy with Just a Sashimi Knife.","tags":"Action,Fantasy,Mystery,School,Life,Supernatural,Drama,Ecchi,Long,Strip,Adaptation,Web,Comic,Full,Color,Reincarnation,Isekai,Video,Games,Demons","author":"GMAN","status":"OnGoing","content":"&quotIf I slash, it will be cut.&quotI, who was once called the best swordsman in the nation, have ended up in a mobile game I&#039ve only spent money on a few times. And I’ve even received the blessing of the &#039Sword God&#039!But… the only weapon I can use is a sashimi knife?Just one minute a day. I become a Sword Saint with a sashimi knife.","pic":"https:\/\/manhuaplus.org\/uploads\/covers\/conquering-the-academy-with-just-a-sashimi-knife.jpg"}