{"id":"512","name":"Genius Archers Streaming","tags":"Action,Adventure,Long,Strip,Full,Color,Virtual,Reality,Sports","author":"Mung Mung Kim","status":"OnGoing","content":"Yoo Sanghyun, once the youngest champion in a national archery competition and a highly promising talent, saw his dreams shattered by a tragic accident that rendered him unable to handle a bow ever again.Now, as a fallen prodigy, he faced the additional setback of being fired from the company he had joined. In order to make a living, he took on the persona of Almond and embarked on a new path as a gaming streamer.[You have selected the bow.]Swish! Thunk![Headshot!]“Are bosses supposed to be defe","pic":"https:\/\/manhuaplus.org\/uploads\/covers\/genius-archer-s-streaming.jpg"}